LICENSE
MANIFEST.in
README.rst
setup.py
version.txt
HelloWorld/__init__.py
HelloWorld/challenge.py
HelloWorld/result.txt
HelloWorld/sample.txt
HelloWorld/test.py
bin/challenge
challenges/__init__.py
challenges/challenge.py
challenges/conf.py
challenges/main.py
challenges/runner.py
challenges/scaffold.py
challenges/version.txt
challenges.egg-info/PKG-INFO
challenges.egg-info/SOURCES.txt
challenges.egg-info/dependency_links.txt
challenges.egg-info/entry_points.txt
challenges.egg-info/top_level.txt
docs/.DS_Store
docs/HelloFasta.rst
docs/HelloGraph.rst
docs/HelloWorld.rst
docs/Makefile
docs/README.rst
docs/challenges.rst
docs/conf.py
docs/index.rst
docs/modules.rst
docs/tests.rst
docs/_build/.DS_Store
docs/_build/doctrees/HelloFasta.doctree
docs/_build/doctrees/HelloGraph.doctree
docs/_build/doctrees/HelloWorld.doctree
docs/_build/doctrees/README.doctree
docs/_build/doctrees/challenges.doctree
docs/_build/doctrees/environment.pickle
docs/_build/doctrees/index.doctree
docs/_build/doctrees/tests.doctree
docs/_build/doctrees/images/https/readthedocs.org/projects/challenges/badge/version=latest/2ab401aa19a48e7f1636e69b444330b989cd3602
docs/_static/.gitkeep
documentation/epub/.buildinfo
documentation/epub/Challenges.epub
documentation/epub/HelloFasta.xhtml
documentation/epub/HelloGraph.xhtml
documentation/epub/HelloWorld.xhtml
documentation/epub/README.xhtml
documentation/epub/challenges.xhtml
documentation/epub/content.opf
documentation/epub/genindex.xhtml
documentation/epub/index.xhtml
documentation/epub/mimetype
documentation/epub/nav.xhtml
documentation/epub/py-modindex.xhtml
documentation/epub/tests.xhtml
documentation/epub/toc.ncx
documentation/epub/META-INF/container.xml
documentation/epub/_modules/index.xhtml
documentation/epub/_modules/HelloFasta/challenge.xhtml
documentation/epub/_modules/HelloFasta/test.xhtml
documentation/epub/_modules/HelloGraph/challenge.xhtml
documentation/epub/_modules/HelloGraph/test.xhtml
documentation/epub/_modules/HelloWorld/challenge.xhtml
documentation/epub/_modules/HelloWorld/test.xhtml
documentation/epub/_modules/challenges/challenge.xhtml
documentation/epub/_modules/challenges/conf.xhtml
