Metadata-Version: 1.1
Name: challenges
Version: 1.4.0
Summary: Library to assist programming, testing and execution of solutions for coding challenges like those on stepik.org orrosalind.info
Home-page: https://github.com/elmar-hinz/Python.Challenges
Author: Elmar Hinz
Author-email: t3elmar@gmail.com
License: MIT
Keywords: education challenges bioinformatics Coursera Stepik Rosalind
Platform: UNKNOWN
Classifier: Development Status :: 4 - Beta
Classifier: Environment :: Console
Classifier: Intended Audience :: Education
Classifier: License :: OSI Approved :: MIT License
Classifier: Natural Language :: English
Classifier: Programming Language :: Python :: 3
Classifier: Topic :: Education :: Computer Aided Instruction (CAI)
